dsciencelib/package_data.dat
dsciencelib/__init__.py
dsciencelib-1.0.1.data/data/my_data/data_file
dsciencelib-1.0.1.dist-info/WHEEL
dsciencelib-1.0.1.dist-info/metadata.json
dsciencelib-1.0.1.dist-info/RECORD
dsciencelib-1.0.1.dist-info/entry_points.txt
dsciencelib-1.0.1.dist-info/top_level.txt
dsciencelib-1.0.1.dist-info/DESCRIPTION.rst
dsciencelib-1.0.1.dist-info/METADATA
